{"IO":{"INDICATIVO":{"PRESENTE":"io bulico","IMPERFETTO":"io bulicavo","PASSATO_REMOTO":"io bulicai","FUTURO_SEMPLICE":"io bulicherò","PASSATO_PROSSIMO":"io ho bulicato","TRAPASSATO_PROSSIMO":"io avevo bulicato","FUTURO_ANTERIORE":"io avrò bulicato"},"CONGIUNTIVO":{"PRESENTE":"che io bulichi","IMPERFETTO":"che io bulicassi","PASSATO":"che io abbia bulicato","TRAPASSATO":"che io avessi bulicato"},"PRESENTE":{"CONDIZIONALE":"io bulicherei","INFINITO":"bulicare","PARTICIPIO":"bulicante","GERUNDIO":"bulicando"},"PASSATO":{"CONDIZIONALE":"io avrei bulicato","INFINITO":"avere bulicato","PARTICIPIO":"bulicato","GERUNDIO":"avendo bulicato"}},"TU":{"INDICATIVO":{"PRESENTE":"tu bulichi","IMPERFETTO":"tu bulicavi","PASSATO_REMOTO":"tu bulicasti","FUTURO_SEMPLICE":"tu bulicherai","PASSATO_PROSSIMO":"tu hai bulicato","TRAPASSATO_PROSSIMO":"tu avevi bulicato","FUTURO_ANTERIORE":"tu avrai bulicato"},"CONGIUNTIVO":{"PRESENTE":"che tu bulichi","IMPERFETTO":"che tu bulicassi","PASSATO":"che tu abbia bulicato","TRAPASSATO":"che tu avessi bulicato"},"PRESENTE":{"CONDIZIONALE":"tu bulicheresti","IMPERATIVO":"bulica","INFINITO":"bulicare","PARTICIPIO":"bulicante","GERUNDIO":"bulicando"},"PASSATO":{"CONDIZIONALE":"tu avresti bulicato","INFINITO":"avere bulicato","PARTICIPIO":"bulicato","GERUNDIO":"avendo bulicato"}},"LUI_LEI":{"INDICATIVO":{"PRESENTE":"lui/lei bulica","IMPERFETTO":"lui/lei bulicava","PASSATO_REMOTO":"lui/lei bulicò","FUTURO_SEMPLICE":"lui/lei bulicherà","PASSATO_PROSSIMO":"lui/lei ha bulicato","TRAPASSATO_PROSSIMO":"lui/lei aveva bulicato","FUTURO_ANTERIORE":"lui/lei avrà bulicato"},"CONGIUNTIVO":{"PRESENTE":"che lui/lei bulichi","IMPERFETTO":"che lui/lei bulicasse","PASSATO":"che lui/lei abbia bulicato","TRAPASSATO":"che lui/lei avesse bulicato"},"PRESENTE":{"CONDIZIONALE":"lui/lei bulicherebbe","IMPERATIVO":"bulichi","INFINITO":"bulicare","PARTICIPIO":"bulicante","GERUNDIO":"bulicando"},"PASSATO":{"CONDIZIONALE":"lui/lei avrebbe bulicato","INFINITO":"avere bulicato","PARTICIPIO":"bulicato","GERUNDIO":"avendo bulicato"}},"NOI":{"INDICATIVO":{"PRESENTE":"noi bulichiamo","IMPERFETTO":"noi bulicavamo","PASSATO_REMOTO":"noi bulicammo","FUTURO_SEMPLICE":"noi bulicheremo","PASSATO_PROSSIMO":"noi abbiamo bulicato","TRAPASSATO_PROSSIMO":"noi avevamo bulicato","FUTURO_ANTERIORE":"noi avremo bulicato"},"CONGIUNTIVO":{"PRESENTE":"che noi bulichiamo","IMPERFETTO":"che noi bulicassimo","PASSATO":"che noi abbiamo bulicato","TRAPASSATO":"che noi avessimo bulicato"},"PRESENTE":{"CONDIZIONALE":"noi bulicheremmo","IMPERATIVO":"bulichiamo","INFINITO":"bulicare","PARTICIPIO":"bulicante","GERUNDIO":"bulicando"},"PASSATO":{"CONDIZIONALE":"noi avremmo bulicato","INFINITO":"avere bulicato","PARTICIPIO":"bulicato","GERUNDIO":"avendo bulicato"}},"VOI":{"INDICATIVO":{"PRESENTE":"voi bulicate","IMPERFETTO":"voi bulicavate","PASSATO_REMOTO":"voi bulicaste","FUTURO_SEMPLICE":"voi bulicherete","PASSATO_PROSSIMO":"voi avete bulicato","TRAPASSATO_PROSSIMO":"voi avevate bulicato","FUTURO_ANTERIORE":"voi avrete bulicato"},"CONGIUNTIVO":{"PRESENTE":"che voi bulichiate","IMPERFETTO":"che voi bulicaste","PASSATO":"che voi abbiate bulicato","TRAPASSATO":"che voi aveste bulicato"},"PRESENTE":{"CONDIZIONALE":"voi bulichereste","IMPERATIVO":"bulicate","INFINITO":"bulicare","PARTICIPIO":"bulicante","GERUNDIO":"bulicando"},"PASSATO":{"CONDIZIONALE":"voi avreste bulicato","INFINITO":"avere bulicato","PARTICIPIO":"bulicato","GERUNDIO":"avendo bulicato"}},"LORO":{"INDICATIVO":{"PRESENTE":"loro bulicano","IMPERFETTO":"loro bulicavano","PASSATO_REMOTO":"loro bulicarono","FUTURO_SEMPLICE":"loro bulicheranno","PASSATO_PROSSIMO":"loro hanno bulicato","TRAPASSATO_PROSSIMO":"loro avevano bulicato","FUTURO_ANTERIORE":"loro avranno bulicato"},"CONGIUNTIVO":{"PRESENTE":"che loro bulichino","IMPERFETTO":"che loro bulicassero","PASSATO":"che loro abbiano bulicato","TRAPASSATO":"che loro avessero bulicato"},"PRESENTE":{"CONDIZIONALE":"loro bulicherebbero","IMPERATIVO":"bulichino","INFINITO":"bulicare","PARTICIPIO":"bulicante","GERUNDIO":"bulicando"},"PASSATO":{"CONDIZIONALE":"loro avrebbero bulicato","INFINITO":"avere bulicato","PARTICIPIO":"bulicato","GERUNDIO":"avendo bulicato"}}}