{"IO":{"INDICATIVO":{"PRESENTE":"io incerpico","IMPERFETTO":"io incerpicavo","PASSATO_REMOTO":"io incerpicai","FUTURO_SEMPLICE":"io incerpicherò","PASSATO_PROSSIMO":"io ho incerpicato","TRAPASSATO_PROSSIMO":"io avevo incerpicato","FUTURO_ANTERIORE":"io avrò incerpicato"},"CONGIUNTIVO":{"PRESENTE":"che io incerpichi","IMPERFETTO":"che io incerpicassi","PASSATO":"che io abbia incerpicato","TRAPASSATO":"che io avessi incerpicato"},"PRESENTE":{"CONDIZIONALE":"io incerpicherei","INFINITO":"incerpicare","PARTICIPIO":"incerpicante","GERUNDIO":"incerpicando"},"PASSATO":{"CONDIZIONALE":"io avrei incerpicato","INFINITO":"avere incerpicato","PARTICIPIO":"incerpicato","GERUNDIO":"avendo incerpicato"}},"TU":{"INDICATIVO":{"PRESENTE":"tu incerpichi","IMPERFETTO":"tu incerpicavi","PASSATO_REMOTO":"tu incerpicasti","FUTURO_SEMPLICE":"tu incerpicherai","PASSATO_PROSSIMO":"tu hai incerpicato","TRAPASSATO_PROSSIMO":"tu avevi incerpicato","FUTURO_ANTERIORE":"tu avrai incerpicato"},"CONGIUNTIVO":{"PRESENTE":"che tu incerpichi","IMPERFETTO":"che tu incerpicassi","PASSATO":"che tu abbia incerpicato","TRAPASSATO":"che tu avessi incerpicato"},"PRESENTE":{"CONDIZIONALE":"tu incerpicheresti","IMPERATIVO":"incerpica","INFINITO":"incerpicare","PARTICIPIO":"incerpicante","GERUNDIO":"incerpicando"},"PASSATO":{"CONDIZIONALE":"tu avresti incerpicato","INFINITO":"avere incerpicato","PARTICIPIO":"incerpicato","GERUNDIO":"avendo incerpicato"}},"LUI_LEI":{"INDICATIVO":{"PRESENTE":"lui/lei incerpica","IMPERFETTO":"lui/lei incerpicava","PASSATO_REMOTO":"lui/lei incerpicò","FUTURO_SEMPLICE":"lui/lei incerpicherà","PASSATO_PROSSIMO":"lui/lei ha incerpicato","TRAPASSATO_PROSSIMO":"lui/lei aveva incerpicato","FUTURO_ANTERIORE":"lui/lei avrà incerpicato"},"CONGIUNTIVO":{"PRESENTE":"che lui/lei incerpichi","IMPERFETTO":"che lui/lei incerpicasse","PASSATO":"che lui/lei abbia incerpicato","TRAPASSATO":"che lui/lei avesse incerpicato"},"PRESENTE":{"CONDIZIONALE":"lui/lei incerpicherebbe","IMPERATIVO":"incerpichi","INFINITO":"incerpicare","PARTICIPIO":"incerpicante","GERUNDIO":"incerpicando"},"PASSATO":{"CONDIZIONALE":"lui/lei avrebbe incerpicato","INFINITO":"avere incerpicato","PARTICIPIO":"incerpicato","GERUNDIO":"avendo incerpicato"}},"NOI":{"INDICATIVO":{"PRESENTE":"noi incerpichiamo","IMPERFETTO":"noi incerpicavamo","PASSATO_REMOTO":"noi incerpicammo","FUTURO_SEMPLICE":"noi incerpicheremo","PASSATO_PROSSIMO":"noi abbiamo incerpicato","TRAPASSATO_PROSSIMO":"noi avevamo incerpicato","FUTURO_ANTERIORE":"noi avremo incerpicato"},"CONGIUNTIVO":{"PRESENTE":"che noi incerpichiamo","IMPERFETTO":"che noi incerpicassimo","PASSATO":"che noi abbiamo incerpicato","TRAPASSATO":"che noi avessimo incerpicato"},"PRESENTE":{"CONDIZIONALE":"noi incerpicheremmo","IMPERATIVO":"incerpichiamo","INFINITO":"incerpicare","PARTICIPIO":"incerpicante","GERUNDIO":"incerpicando"},"PASSATO":{"CONDIZIONALE":"noi avremmo incerpicato","INFINITO":"avere incerpicato","PARTICIPIO":"incerpicato","GERUNDIO":"avendo incerpicato"}},"VOI":{"INDICATIVO":{"PRESENTE":"voi incerpicate","IMPERFETTO":"voi incerpicavate","PASSATO_REMOTO":"voi incerpicaste","FUTURO_SEMPLICE":"voi incerpicherete","PASSATO_PROSSIMO":"voi avete incerpicato","TRAPASSATO_PROSSIMO":"voi avevate incerpicato","FUTURO_ANTERIORE":"voi avrete incerpicato"},"CONGIUNTIVO":{"PRESENTE":"che voi incerpichiate","IMPERFETTO":"che voi incerpicaste","PASSATO":"che voi abbiate incerpicato","TRAPASSATO":"che voi aveste incerpicato"},"PRESENTE":{"CONDIZIONALE":"voi incerpichereste","IMPERATIVO":"incerpicate","INFINITO":"incerpicare","PARTICIPIO":"incerpicante","GERUNDIO":"incerpicando"},"PASSATO":{"CONDIZIONALE":"voi avreste incerpicato","INFINITO":"avere incerpicato","PARTICIPIO":"incerpicato","GERUNDIO":"avendo incerpicato"}},"LORO":{"INDICATIVO":{"PRESENTE":"loro incerpicano","IMPERFETTO":"loro incerpicavano","PASSATO_REMOTO":"loro incerpicarono","FUTURO_SEMPLICE":"loro incerpicheranno","PASSATO_PROSSIMO":"loro hanno incerpicato","TRAPASSATO_PROSSIMO":"loro avevano incerpicato","FUTURO_ANTERIORE":"loro avranno incerpicato"},"CONGIUNTIVO":{"PRESENTE":"che loro incerpichino","IMPERFETTO":"che loro incerpicassero","PASSATO":"che loro abbiano incerpicato","TRAPASSATO":"che loro avessero incerpicato"},"PRESENTE":{"CONDIZIONALE":"loro incerpicherebbero","IMPERATIVO":"incerpichino","INFINITO":"incerpicare","PARTICIPIO":"incerpicante","GERUNDIO":"incerpicando"},"PASSATO":{"CONDIZIONALE":"loro avrebbero incerpicato","INFINITO":"avere incerpicato","PARTICIPIO":"incerpicato","GERUNDIO":"avendo incerpicato"}}}