{"IO":{"INDICATIVO":{"PRESENTE":"io pedalizzo","IMPERFETTO":"io pedalizzavo","PASSATO_REMOTO":"io pedalizzai","FUTURO_SEMPLICE":"io pedalizzerò","PASSATO_PROSSIMO":"io ho pedalizzato","TRAPASSATO_PROSSIMO":"io avevo pedalizzato","FUTURO_ANTERIORE":"io avrò pedalizzato"},"CONGIUNTIVO":{"PRESENTE":"che io pedalizzi","IMPERFETTO":"che io pedalizzassi","PASSATO":"che io abbia pedalizzato","TRAPASSATO":"che io avessi pedalizzato"},"PRESENTE":{"CONDIZIONALE":"io pedalizzerei","INFINITO":"pedalizzare","PARTICIPIO":"pedalizzante","GERUNDIO":"pedalizzando"},"PASSATO":{"CONDIZIONALE":"io avrei pedalizzato","INFINITO":"avere pedalizzato","PARTICIPIO":"pedalizzato","GERUNDIO":"avendo pedalizzato"}},"TU":{"INDICATIVO":{"PRESENTE":"tu pedalizzi","IMPERFETTO":"tu pedalizzavi","PASSATO_REMOTO":"tu pedalizzasti","FUTURO_SEMPLICE":"tu pedalizzerai","PASSATO_PROSSIMO":"tu hai pedalizzato","TRAPASSATO_PROSSIMO":"tu avevi pedalizzato","FUTURO_ANTERIORE":"tu avrai pedalizzato"},"CONGIUNTIVO":{"PRESENTE":"che tu pedalizzi","IMPERFETTO":"che tu pedalizzassi","PASSATO":"che tu abbia pedalizzato","TRAPASSATO":"che tu avessi pedalizzato"},"PRESENTE":{"CONDIZIONALE":"tu pedalizzeresti","IMPERATIVO":"pedalizza","INFINITO":"pedalizzare","PARTICIPIO":"pedalizzante","GERUNDIO":"pedalizzando"},"PASSATO":{"CONDIZIONALE":"tu avresti pedalizzato","INFINITO":"avere pedalizzato","PARTICIPIO":"pedalizzato","GERUNDIO":"avendo pedalizzato"}},"LUI_LEI":{"INDICATIVO":{"PRESENTE":"lui/lei pedalizza","IMPERFETTO":"lui/lei pedalizzava","PASSATO_REMOTO":"lui/lei pedalizzò","FUTURO_SEMPLICE":"lui/lei pedalizzerà","PASSATO_PROSSIMO":"lui/lei ha pedalizzato","TRAPASSATO_PROSSIMO":"lui/lei aveva pedalizzato","FUTURO_ANTERIORE":"lui/lei avrà pedalizzato"},"CONGIUNTIVO":{"PRESENTE":"che lui/lei pedalizzi","IMPERFETTO":"che lui/lei pedalizzasse","PASSATO":"che lui/lei abbia pedalizzato","TRAPASSATO":"che lui/lei avesse pedalizzato"},"PRESENTE":{"CONDIZIONALE":"lui/lei pedalizzerebbe","IMPERATIVO":"pedalizzi","INFINITO":"pedalizzare","PARTICIPIO":"pedalizzante","GERUNDIO":"pedalizzando"},"PASSATO":{"CONDIZIONALE":"lui/lei avrebbe pedalizzato","INFINITO":"avere pedalizzato","PARTICIPIO":"pedalizzato","GERUNDIO":"avendo pedalizzato"}},"NOI":{"INDICATIVO":{"PRESENTE":"noi pedalizziamo","IMPERFETTO":"noi pedalizzavamo","PASSATO_REMOTO":"noi pedalizzammo","FUTURO_SEMPLICE":"noi pedalizzeremo","PASSATO_PROSSIMO":"noi abbiamo pedalizzato","TRAPASSATO_PROSSIMO":"noi avevamo pedalizzato","FUTURO_ANTERIORE":"noi avremo pedalizzato"},"CONGIUNTIVO":{"PRESENTE":"che noi pedalizziamo","IMPERFETTO":"che noi pedalizzassimo","PASSATO":"che noi abbiamo pedalizzato","TRAPASSATO":"che noi avessimo pedalizzato"},"PRESENTE":{"CONDIZIONALE":"noi pedalizzeremmo","IMPERATIVO":"pedalizziamo","INFINITO":"pedalizzare","PARTICIPIO":"pedalizzante","GERUNDIO":"pedalizzando"},"PASSATO":{"CONDIZIONALE":"noi avremmo pedalizzato","INFINITO":"avere pedalizzato","PARTICIPIO":"pedalizzato","GERUNDIO":"avendo pedalizzato"}},"VOI":{"INDICATIVO":{"PRESENTE":"voi pedalizzate","IMPERFETTO":"voi pedalizzavate","PASSATO_REMOTO":"voi pedalizzaste","FUTURO_SEMPLICE":"voi pedalizzerete","PASSATO_PROSSIMO":"voi avete pedalizzato","TRAPASSATO_PROSSIMO":"voi avevate pedalizzato","FUTURO_ANTERIORE":"voi avrete pedalizzato"},"CONGIUNTIVO":{"PRESENTE":"che voi pedalizziate","IMPERFETTO":"che voi pedalizzaste","PASSATO":"che voi abbiate pedalizzato","TRAPASSATO":"che voi aveste pedalizzato"},"PRESENTE":{"CONDIZIONALE":"voi pedalizzereste","IMPERATIVO":"pedalizzate","INFINITO":"pedalizzare","PARTICIPIO":"pedalizzante","GERUNDIO":"pedalizzando"},"PASSATO":{"CONDIZIONALE":"voi avreste pedalizzato","INFINITO":"avere pedalizzato","PARTICIPIO":"pedalizzato","GERUNDIO":"avendo pedalizzato"}},"LORO":{"INDICATIVO":{"PRESENTE":"loro pedalizzano","IMPERFETTO":"loro pedalizzavano","PASSATO_REMOTO":"loro pedalizzarono","FUTURO_SEMPLICE":"loro pedalizzeranno","PASSATO_PROSSIMO":"loro hanno pedalizzato","TRAPASSATO_PROSSIMO":"loro avevano pedalizzato","FUTURO_ANTERIORE":"loro avranno pedalizzato"},"CONGIUNTIVO":{"PRESENTE":"che loro pedalizzino","IMPERFETTO":"che loro pedalizzassero","PASSATO":"che loro abbiano pedalizzato","TRAPASSATO":"che loro avessero pedalizzato"},"PRESENTE":{"CONDIZIONALE":"loro pedalizzerebbero","IMPERATIVO":"pedalizzino","INFINITO":"pedalizzare","PARTICIPIO":"pedalizzante","GERUNDIO":"pedalizzando"},"PASSATO":{"CONDIZIONALE":"loro avrebbero pedalizzato","INFINITO":"avere pedalizzato","PARTICIPIO":"pedalizzato","GERUNDIO":"avendo pedalizzato"}}}