{"IO":{"INDICATIVO":{"PRESENTE":"io promino","IMPERFETTO":"io prominevo","PASSATO_REMOTO":"io prominetti, prominei","FUTURO_SEMPLICE":"io prominerò","PASSATO_PROSSIMO":"—","TRAPASSATO_PROSSIMO":"—","FUTURO_ANTERIORE":"—"},"CONGIUNTIVO":{"PRESENTE":"che io promina","IMPERFETTO":"che io prominessi","PASSATO":"—","TRAPASSATO":"—"},"PRESENTE":{"CONDIZIONALE":"io prominerei","INFINITO":"prominere","PARTICIPIO":"prominente","GERUNDIO":"prominendo"},"PASSATO":{"CONDIZIONALE":"—","INFINITO":"—","PARTICIPIO":"—","GERUNDIO":"—"}},"TU":{"INDICATIVO":{"PRESENTE":"tu promini","IMPERFETTO":"tu prominevi","PASSATO_REMOTO":"tu prominesti","FUTURO_SEMPLICE":"tu prominerai","PASSATO_PROSSIMO":"—","TRAPASSATO_PROSSIMO":"—","FUTURO_ANTERIORE":"—"},"CONGIUNTIVO":{"PRESENTE":"che tu promina","IMPERFETTO":"che tu prominessi","PASSATO":"—","TRAPASSATO":"—"},"PRESENTE":{"CONDIZIONALE":"tu promineresti","IMPERATIVO":"promini","INFINITO":"prominere","PARTICIPIO":"prominente","GERUNDIO":"prominendo"},"PASSATO":{"CONDIZIONALE":"—","INFINITO":"—","PARTICIPIO":"—","GERUNDIO":"—"}},"LUI_LEI":{"INDICATIVO":{"PRESENTE":"lui/lei promine","IMPERFETTO":"lui/lei promineva","PASSATO_REMOTO":"lui/lei prominette, prominé","FUTURO_SEMPLICE":"lui/lei prominerà","PASSATO_PROSSIMO":"—","TRAPASSATO_PROSSIMO":"—","FUTURO_ANTERIORE":"—"},"CONGIUNTIVO":{"PRESENTE":"che lui/lei promina","IMPERFETTO":"che lui/lei prominesse","PASSATO":"—","TRAPASSATO":"—"},"PRESENTE":{"CONDIZIONALE":"lui/lei prominerebbe","IMPERATIVO":"promina","INFINITO":"prominere","PARTICIPIO":"prominente","GERUNDIO":"prominendo"},"PASSATO":{"CONDIZIONALE":"—","INFINITO":"—","PARTICIPIO":"—","GERUNDIO":"—"}},"NOI":{"INDICATIVO":{"PRESENTE":"noi prominiamo","IMPERFETTO":"noi prominevamo","PASSATO_REMOTO":"noi prominemmo","FUTURO_SEMPLICE":"noi promineremo","PASSATO_PROSSIMO":"—","TRAPASSATO_PROSSIMO":"—","FUTURO_ANTERIORE":"—"},"CONGIUNTIVO":{"PRESENTE":"che noi prominiamo","IMPERFETTO":"che noi prominessimo","PASSATO":"—","TRAPASSATO":"—"},"PRESENTE":{"CONDIZIONALE":"noi promineremmo","IMPERATIVO":"prominiamo","INFINITO":"prominere","PARTICIPIO":"prominente","GERUNDIO":"prominendo"},"PASSATO":{"CONDIZIONALE":"—","INFINITO":"—","PARTICIPIO":"—","GERUNDIO":"—"}},"VOI":{"INDICATIVO":{"PRESENTE":"voi prominete","IMPERFETTO":"voi prominevate","PASSATO_REMOTO":"voi promineste","FUTURO_SEMPLICE":"voi prominerete","PASSATO_PROSSIMO":"—","TRAPASSATO_PROSSIMO":"—","FUTURO_ANTERIORE":"—"},"CONGIUNTIVO":{"PRESENTE":"che voi prominiate","IMPERFETTO":"che voi promineste","PASSATO":"—","TRAPASSATO":"—"},"PRESENTE":{"CONDIZIONALE":"voi prominereste","IMPERATIVO":"prominete","INFINITO":"prominere","PARTICIPIO":"prominente","GERUNDIO":"prominendo"},"PASSATO":{"CONDIZIONALE":"—","INFINITO":"—","PARTICIPIO":"—","GERUNDIO":"—"}},"LORO":{"INDICATIVO":{"PRESENTE":"loro prominono","IMPERFETTO":"loro prominevano","PASSATO_REMOTO":"loro prominettero, prominerono","FUTURO_SEMPLICE":"loro promineranno","PASSATO_PROSSIMO":"—","TRAPASSATO_PROSSIMO":"—","FUTURO_ANTERIORE":"—"},"CONGIUNTIVO":{"PRESENTE":"che loro prominano","IMPERFETTO":"che loro prominessero","PASSATO":"—","TRAPASSATO":"—"},"PRESENTE":{"CONDIZIONALE":"loro prominerebbero","IMPERATIVO":"prominano","INFINITO":"prominere","PARTICIPIO":"prominente","GERUNDIO":"prominendo"},"PASSATO":{"CONDIZIONALE":"—","INFINITO":"—","PARTICIPIO":"—","GERUNDIO":"—"}}}