{"IO":{"INDICATIVO":{"PRESENTE":"io sbriaco","IMPERFETTO":"io sbriacavo","PASSATO_REMOTO":"io sbriacai","FUTURO_SEMPLICE":"io sbriacherò","PASSATO_PROSSIMO":"io sono sbriacato/a","TRAPASSATO_PROSSIMO":"io ero sbriacato/a","FUTURO_ANTERIORE":"io sarò sbriacato/a"},"CONGIUNTIVO":{"PRESENTE":"che io sbriachi","IMPERFETTO":"che io sbriacassi","PASSATO":"che io sia sbriacato/a","TRAPASSATO":"che io fossi sbriacato/a"},"PRESENTE":{"CONDIZIONALE":"io sbriacherei","INFINITO":"sbriacare","PARTICIPIO":"sbriacante","GERUNDIO":"sbriacando"},"PASSATO":{"CONDIZIONALE":"io sarei sbriacato/a","INFINITO":"essere sbriacato/a/i/e","PARTICIPIO":"sbriacato/a/i/e","GERUNDIO":"essendo sbriacato/a/i/e"}},"TU":{"INDICATIVO":{"PRESENTE":"tu sbriachi","IMPERFETTO":"tu sbriacavi","PASSATO_REMOTO":"tu sbriacasti","FUTURO_SEMPLICE":"tu sbriacherai","PASSATO_PROSSIMO":"tu sei sbriacato/a","TRAPASSATO_PROSSIMO":"tu eri sbriacato/a","FUTURO_ANTERIORE":"tu sarai sbriacato/a"},"CONGIUNTIVO":{"PRESENTE":"che tu sbriachi","IMPERFETTO":"che tu sbriacassi","PASSATO":"che tu sia sbriacato/a","TRAPASSATO":"che tu fossi sbriacato/a"},"PRESENTE":{"CONDIZIONALE":"tu sbriacheresti","IMPERATIVO":"sbriaca","INFINITO":"sbriacare","PARTICIPIO":"sbriacante","GERUNDIO":"sbriacando"},"PASSATO":{"CONDIZIONALE":"tu saresti sbriacato/a","INFINITO":"essere sbriacato/a/i/e","PARTICIPIO":"sbriacato/a/i/e","GERUNDIO":"essendo sbriacato/a/i/e"}},"LUI_LEI":{"INDICATIVO":{"PRESENTE":"lui/lei sbriaca","IMPERFETTO":"lui/lei sbriacava","PASSATO_REMOTO":"lui/lei sbriacò","FUTURO_SEMPLICE":"lui/lei sbriacherà","PASSATO_PROSSIMO":"lui/lei è sbriacato/a","TRAPASSATO_PROSSIMO":"lui/lei era sbriacato/a","FUTURO_ANTERIORE":"lui/lei sarà sbriacato/a"},"CONGIUNTIVO":{"PRESENTE":"che lui/lei sbriachi","IMPERFETTO":"che lui/lei sbriacasse","PASSATO":"che lui/lei sia sbriacato/a","TRAPASSATO":"che lui/lei fosse sbriacato/a"},"PRESENTE":{"CONDIZIONALE":"lui/lei sbriacherebbe","IMPERATIVO":"sbriachi","INFINITO":"sbriacare","PARTICIPIO":"sbriacante","GERUNDIO":"sbriacando"},"PASSATO":{"CONDIZIONALE":"lui/lei sarebbe sbriacato/a","INFINITO":"essere sbriacato/a/i/e","PARTICIPIO":"sbriacato/a/i/e","GERUNDIO":"essendo sbriacato/a/i/e"}},"NOI":{"INDICATIVO":{"PRESENTE":"noi sbriachiamo","IMPERFETTO":"noi sbriacavamo","PASSATO_REMOTO":"noi sbriacammo","FUTURO_SEMPLICE":"noi sbriacheremo","PASSATO_PROSSIMO":"noi siamo sbriacati/e","TRAPASSATO_PROSSIMO":"noi eravamo sbriacati/e","FUTURO_ANTERIORE":"noi saremo sbriacati/e"},"CONGIUNTIVO":{"PRESENTE":"che noi sbriachiamo","IMPERFETTO":"che noi sbriacassimo","PASSATO":"che noi siamo sbriacati/e","TRAPASSATO":"che noi fossimo sbriacati/e"},"PRESENTE":{"CONDIZIONALE":"noi sbriacheremmo","IMPERATIVO":"sbriachiamo","INFINITO":"sbriacare","PARTICIPIO":"sbriacante","GERUNDIO":"sbriacando"},"PASSATO":{"CONDIZIONALE":"noi saremmo sbriacati/e","INFINITO":"essere sbriacato/a/i/e","PARTICIPIO":"sbriacato/a/i/e","GERUNDIO":"essendo sbriacato/a/i/e"}},"VOI":{"INDICATIVO":{"PRESENTE":"voi sbriacate","IMPERFETTO":"voi sbriacavate","PASSATO_REMOTO":"voi sbriacaste","FUTURO_SEMPLICE":"voi sbriacherete","PASSATO_PROSSIMO":"voi siete sbriacati/e","TRAPASSATO_PROSSIMO":"voi eravate sbriacati/e","FUTURO_ANTERIORE":"voi sarete sbriacati/e"},"CONGIUNTIVO":{"PRESENTE":"che voi sbriachiate","IMPERFETTO":"che voi sbriacaste","PASSATO":"che voi siate sbriacati/e","TRAPASSATO":"che voi foste sbriacati/e"},"PRESENTE":{"CONDIZIONALE":"voi sbriachereste","IMPERATIVO":"sbriacate","INFINITO":"sbriacare","PARTICIPIO":"sbriacante","GERUNDIO":"sbriacando"},"PASSATO":{"CONDIZIONALE":"voi sareste sbriacati/e","INFINITO":"essere sbriacato/a/i/e","PARTICIPIO":"sbriacato/a/i/e","GERUNDIO":"essendo sbriacato/a/i/e"}},"LORO":{"INDICATIVO":{"PRESENTE":"loro sbriacano","IMPERFETTO":"loro sbriacavano","PASSATO_REMOTO":"loro sbriacarono","FUTURO_SEMPLICE":"loro sbriacheranno","PASSATO_PROSSIMO":"loro sono sbriacati/e","TRAPASSATO_PROSSIMO":"loro erano sbriacati/e","FUTURO_ANTERIORE":"loro saranno sbriacati/e"},"CONGIUNTIVO":{"PRESENTE":"che loro sbriachino","IMPERFETTO":"che loro sbriacassero","PASSATO":"che loro siano sbriacati/e","TRAPASSATO":"che loro fossero sbriacati/e"},"PRESENTE":{"CONDIZIONALE":"loro sbriacherebbero","IMPERATIVO":"sbriachino","INFINITO":"sbriacare","PARTICIPIO":"sbriacante","GERUNDIO":"sbriacando"},"PASSATO":{"CONDIZIONALE":"loro sarebbero sbriacati/e","INFINITO":"essere sbriacato/a/i/e","PARTICIPIO":"sbriacato/a/i/e","GERUNDIO":"essendo sbriacato/a/i/e"}}}