{"IO":{"INDICATIVO":{"PRESENTE":"io trapunto","IMPERFETTO":"io trapuntavo","PASSATO_REMOTO":"io trapuntai","FUTURO_SEMPLICE":"io trapunterò","PASSATO_PROSSIMO":"io ho trapuntato","TRAPASSATO_PROSSIMO":"io avevo trapuntato","FUTURO_ANTERIORE":"io avrò trapuntato"},"CONGIUNTIVO":{"PRESENTE":"che io trapunti","IMPERFETTO":"che io trapuntassi","PASSATO":"che io abbia trapuntato","TRAPASSATO":"che io avessi trapuntato"},"PRESENTE":{"CONDIZIONALE":"io trapunterei","INFINITO":"trapuntare","PARTICIPIO":"trapuntante","GERUNDIO":"trapuntando"},"PASSATO":{"CONDIZIONALE":"io avrei trapuntato","INFINITO":"avere trapuntato","PARTICIPIO":"trapuntato","GERUNDIO":"avendo trapuntato"}},"TU":{"INDICATIVO":{"PRESENTE":"tu trapunti","IMPERFETTO":"tu trapuntavi","PASSATO_REMOTO":"tu trapuntasti","FUTURO_SEMPLICE":"tu trapunterai","PASSATO_PROSSIMO":"tu hai trapuntato","TRAPASSATO_PROSSIMO":"tu avevi trapuntato","FUTURO_ANTERIORE":"tu avrai trapuntato"},"CONGIUNTIVO":{"PRESENTE":"che tu trapunti","IMPERFETTO":"che tu trapuntassi","PASSATO":"che tu abbia trapuntato","TRAPASSATO":"che tu avessi trapuntato"},"PRESENTE":{"CONDIZIONALE":"tu trapunteresti","IMPERATIVO":"trapunta","INFINITO":"trapuntare","PARTICIPIO":"trapuntante","GERUNDIO":"trapuntando"},"PASSATO":{"CONDIZIONALE":"tu avresti trapuntato","INFINITO":"avere trapuntato","PARTICIPIO":"trapuntato","GERUNDIO":"avendo trapuntato"}},"LUI_LEI":{"INDICATIVO":{"PRESENTE":"lui/lei trapunta","IMPERFETTO":"lui/lei trapuntava","PASSATO_REMOTO":"lui/lei trapuntò","FUTURO_SEMPLICE":"lui/lei trapunterà","PASSATO_PROSSIMO":"lui/lei ha trapuntato","TRAPASSATO_PROSSIMO":"lui/lei aveva trapuntato","FUTURO_ANTERIORE":"lui/lei avrà trapuntato"},"CONGIUNTIVO":{"PRESENTE":"che lui/lei trapunti","IMPERFETTO":"che lui/lei trapuntasse","PASSATO":"che lui/lei abbia trapuntato","TRAPASSATO":"che lui/lei avesse trapuntato"},"PRESENTE":{"CONDIZIONALE":"lui/lei trapunterebbe","IMPERATIVO":"trapunti","INFINITO":"trapuntare","PARTICIPIO":"trapuntante","GERUNDIO":"trapuntando"},"PASSATO":{"CONDIZIONALE":"lui/lei avrebbe trapuntato","INFINITO":"avere trapuntato","PARTICIPIO":"trapuntato","GERUNDIO":"avendo trapuntato"}},"NOI":{"INDICATIVO":{"PRESENTE":"noi trapuntiamo","IMPERFETTO":"noi trapuntavamo","PASSATO_REMOTO":"noi trapuntammo","FUTURO_SEMPLICE":"noi trapunteremo","PASSATO_PROSSIMO":"noi abbiamo trapuntato","TRAPASSATO_PROSSIMO":"noi avevamo trapuntato","FUTURO_ANTERIORE":"noi avremo trapuntato"},"CONGIUNTIVO":{"PRESENTE":"che noi trapuntiamo","IMPERFETTO":"che noi trapuntassimo","PASSATO":"che noi abbiamo trapuntato","TRAPASSATO":"che noi avessimo trapuntato"},"PRESENTE":{"CONDIZIONALE":"noi trapunteremmo","IMPERATIVO":"trapuntiamo","INFINITO":"trapuntare","PARTICIPIO":"trapuntante","GERUNDIO":"trapuntando"},"PASSATO":{"CONDIZIONALE":"noi avremmo trapuntato","INFINITO":"avere trapuntato","PARTICIPIO":"trapuntato","GERUNDIO":"avendo trapuntato"}},"VOI":{"INDICATIVO":{"PRESENTE":"voi trapuntate","IMPERFETTO":"voi trapuntavate","PASSATO_REMOTO":"voi trapuntaste","FUTURO_SEMPLICE":"voi trapunterete","PASSATO_PROSSIMO":"voi avete trapuntato","TRAPASSATO_PROSSIMO":"voi avevate trapuntato","FUTURO_ANTERIORE":"voi avrete trapuntato"},"CONGIUNTIVO":{"PRESENTE":"che voi trapuntiate","IMPERFETTO":"che voi trapuntaste","PASSATO":"che voi abbiate trapuntato","TRAPASSATO":"che voi aveste trapuntato"},"PRESENTE":{"CONDIZIONALE":"voi trapuntereste","IMPERATIVO":"trapuntate","INFINITO":"trapuntare","PARTICIPIO":"trapuntante","GERUNDIO":"trapuntando"},"PASSATO":{"CONDIZIONALE":"voi avreste trapuntato","INFINITO":"avere trapuntato","PARTICIPIO":"trapuntato","GERUNDIO":"avendo trapuntato"}},"LORO":{"INDICATIVO":{"PRESENTE":"loro trapuntano","IMPERFETTO":"loro trapuntavano","PASSATO_REMOTO":"loro trapuntarono","FUTURO_SEMPLICE":"loro trapunteranno","PASSATO_PROSSIMO":"loro hanno trapuntato","TRAPASSATO_PROSSIMO":"loro avevano trapuntato","FUTURO_ANTERIORE":"loro avranno trapuntato"},"CONGIUNTIVO":{"PRESENTE":"che loro trapuntino","IMPERFETTO":"che loro trapuntassero","PASSATO":"che loro abbiano trapuntato","TRAPASSATO":"che loro avessero trapuntato"},"PRESENTE":{"CONDIZIONALE":"loro trapunterebbero","IMPERATIVO":"trapuntino","INFINITO":"trapuntare","PARTICIPIO":"trapuntante","GERUNDIO":"trapuntando"},"PASSATO":{"CONDIZIONALE":"loro avrebbero trapuntato","INFINITO":"avere trapuntato","PARTICIPIO":"trapuntato","GERUNDIO":"avendo trapuntato"}}}